taggit_labels/__init__.py
taggit_labels/apps.py
taggit_labels/models.py
taggit_labels/widgets.py
taggit_labels/static/taggit_labels/css/taggit_labels.css
taggit_labels/static/taggit_labels/js/taggit_labels.js
django_taggit_labels-0.7.0.dist-info/AUTHORS.rst
django_taggit_labels-0.7.0.dist-info/LICENSE
django_taggit_labels-0.7.0.dist-info/METADATA
django_taggit_labels-0.7.0.dist-info/WHEEL
django_taggit_labels-0.7.0.dist-info/top_level.txt
django_taggit_labels-0.7.0.dist-info/RECORD
