Metadata-Version: 1.1
Name: django-taggit-labels
Version: 0.7.0
Summary: Alternate labels for django-taggit
Home-page: https://github.com/bennylope/django-taggit-labels
Author: Ben Lopatin
Author-email: ben@wellfire.co
License: BSD
Keywords: django-taggit-labels
Platform: UNKNOWN
Classifier: Development Status :: 3 - Alpha
Classifier: Framework :: Django
Classifier: Intended Audience :: Developers
Classifier: License :: OSI Approved :: BSD License
Classifier: Natural Language :: English
Classifier: Programming Language :: Python :: 2
Classifier: Programming Language :: Python :: 2.6
Classifier: Programming Language :: Python :: 2.7
Classifier: Programming Language :: Python :: 3
Classifier: Programming Language :: Python :: 3.3
